disfv1.py
disfv1-1.0.6.dist-info/LICENSE
disfv1-1.0.6.dist-info/METADATA
disfv1-1.0.6.dist-info/WHEEL
disfv1-1.0.6.dist-info/entry_points.txt
disfv1-1.0.6.dist-info/top_level.txt
disfv1-1.0.6.dist-info/RECORD
