Metadata-Version: 2.1
Name: disfv1
Version: 1.0.6
Summary: FV-1 Disassembler
Home-page: https://github.com/ndf-zz/disfv1
Author: Nathan Fraser
Author-email: ndf@metarace.com.au
License: UNKNOWN
Platform: UNKNOWN
Classifier: Development Status :: 5 - Production/Stable
Classifier: Environment :: Console
Classifier: License :: OSI Approved :: MIT License
Classifier: Programming Language :: Python
Classifier: Topic :: Software Development :: Assemblers
Requires-Python: >2.6
